b26.py
b26-0.0.1.dist-info/METADATA
b26-0.0.1.dist-info/WHEEL
b26-0.0.1.dist-info/top_level.txt
b26-0.0.1.dist-info/RECORD
