Metadata-Version: 2.1
Name: b26
Version: 0.0.1
Summary: Base 26 Encoder and Decoder
Author: phoenixR
License: MIT
Keywords: alphabet,base 26,decoder,encoder
Classifier: Development Status :: 5 - Production/Stable
Classifier: License :: OSI Approved :: MIT License
Classifier: Natural Language :: English
Classifier: Programming Language :: Python :: 3
Classifier: Topic :: Utilities
Classifier: Typing :: Typed
Requires-Python: >=3.7
